s1280238_learn/__init__.py
s1280238_learn/statistics/__init__.py
s1280238_learn/statistics/itemFrequencies.py
s1280238_learn/visualization/__init__.py
s1280238_learn/visualization/heatMap.py
s1280238_learn-0.1.dist-info/METADATA
s1280238_learn-0.1.dist-info/WHEEL
s1280238_learn-0.1.dist-info/top_level.txt
s1280238_learn-0.1.dist-info/RECORD
